pybert/__init__.py
pybert/train_eval.py
pybert/utils.py
pybert/models/__init__.py
pybert/models/bert.py
pybert/pytorch_pretrained/__init__.py
pybert/pytorch_pretrained/file_utils.py
pybert/pytorch_pretrained/modeling.py
pybert/pytorch_pretrained/optimization.py
pybert/pytorch_pretrained/tokenization.py
pybert-0.0.2.dist-info/METADATA
pybert-0.0.2.dist-info/WHEEL
pybert-0.0.2.dist-info/top_level.txt
pybert-0.0.2.dist-info/RECORD
