Metadata-Version: 2.1
Name: pybert
Version: 0.0.2
Summary: 一行代码训练 BERT
Home-page: https://github.com/guofei9987/pybert
Author: Guo Fei
Author-email: guofei9987@foxmail.com
License: MIT
Platform: linux
Platform: windows
Platform: macos
Requires-Python: >=3.5
Requires-Dist: boto3
Requires-Dist: botocore
